README.md
setup.cfg
setup.py
urgent11_detector.py
urgent11_detector.egg-info/PKG-INFO
urgent11_detector.egg-info/SOURCES.txt
urgent11_detector.egg-info/dependency_links.txt
urgent11_detector.egg-info/entry_points.txt
urgent11_detector.egg-info/requires.txt
urgent11_detector.egg-info/top_level.txt