Metadata-Version: 2.1
Name: urgent11-detector
Version: 0.1.1
Summary: URGENT/11 detection tool by Armis
Home-page: https://github.com/ArmisSecurity/urgent11-detector
Author: Armis Inc.
License: UNKNOWN
Project-URL: Armis, http://armis.com
Project-URL: Bug Reports, https://github.com/ArmisSecurity/urgent11-detector/issues
Keywords: windriver vxworks rtos interpeak ipnet urgent/11 urgent11 armis
Platform: UNKNOWN
Classifier: Development Status :: 4 - Beta
Classifier: Intended Audience :: System Administrators
Classifier: Topic :: Security
Classifier: License :: OSI Approved :: GNU General Public License v3 (GPLv3)
Classifier: Programming Language :: Python :: 2
Classifier: Programming Language :: Python :: 2.7
Classifier: Programming Language :: Python :: 3
Classifier: Programming Language :: Python :: 3.5
Classifier: Programming Language :: Python :: 3.6
Classifier: Programming Language :: Python :: 3.7
Requires-Python: >=2.7, !=3.0.*, !=3.1.*, !=3.2.*, !=3.3.*
